{
  "service": {
    "name": "Forensic CPA AI",
    "description": "Forensic auditing tool for bank statements, credit cards, and Venmo - tracks money flow, flags suspicious patterns, and separates personal/business spending.",
    "category": "apps",
    "tags": ["forensic", "accounting", "auditing", "finance", "flask"],
    "tech_stack": ["python", "flask", "sqlite", "pdfplumber"],
    "dependencies": [],
    "config_paths": [],
    "port": null,
    "local_url": "http://localhost:{PORT}",
    "healthcheck_url": "http://localhost:{PORT}/health",
    "working_directory": ".",
    "start_command": "python3 app.py --port={PORT}",
    "stop_command": "kill $(ps aux | grep -E 'python.*(app|run).py' | grep -v grep | awk '{print $2}') 2>/dev/null || true",
    "restart_command": "kill $(ps aux | grep -E 'python.*(app|run).py' | grep -v grep | awk '{print $2}') 2>/dev/null; sleep 2; python3 app.py --port={PORT}",
    "env_overrides": {
      "PORT": "{PORT}"
    },
    "database_id": null,
    "database_connection_string": "sqlite:///data/forensic_audit.db",
    "database_schema_overview": "Tables: accounts, documents, transactions, categories, category_rules, audit_log, proof_links"
  },
  "database": {
    "database_name": "forensic_audit",
    "type": "sqlite",
    "host": "localhost",
    "port": null,
    "username_env": null,
    "password_env": null,
    "connection_string": "sqlite:///data/forensic_audit.db",
    "schema_overview": "Tables: accounts, documents, transactions, categories(25), category_rules(31), audit_log, proof_links"
  },
  "keys": [],
  "requested_port": null,
  "auto_assign_port": true,
  "auto_create_db": false,
  "meta": {}
}
